aiostorage_orm/__init__.py
aiostorage_orm/aiostorage_frame.py
aiostorage_orm/aiostorage_item.py
aiostorage_orm/aiostorage_orm.py
aiostorage_orm/exceptions.py
aiostorage_orm/operation_result.py
aiostorage_orm/redis_impl/__init__.py
aiostorage_orm/redis_impl/aioredis_frame.py
aiostorage_orm/redis_impl/aioredis_item.py
aiostorage_orm/redis_impl/aioredis_orm.py
aiostorage_orm-1.4.5.dist-info/METADATA
aiostorage_orm-1.4.5.dist-info/WHEEL
aiostorage_orm-1.4.5.dist-info/top_level.txt
aiostorage_orm-1.4.5.dist-info/RECORD
