Metadata-Version: 2.1
Name: aiostorage-orm
Version: 1.4.5
Summary: Python for using in-memory storage with ORM
Home-page: https://github.com/CyberPhysics-Platform/aiostorage-orm
Download-URL: https://github.com/CyberPhysics-Platform/aiostorage-orm/archive/refs/heads/master.zip
Author: aarekuha
Author-email: aarekuha@gmail.ru
License: Apache License, Version 2.0
Classifier: License :: OSI Approved :: Apache Software License
Classifier: Operating System :: OS Independent
Classifier: Intended Audience :: End Users/Desktop
Classifier: Intended Audience :: Developers
Classifier: Programming Language :: Python
Classifier: Programming Language :: Python :: 3.9
Classifier: Programming Language :: Python :: 3.10
Classifier: Programming Language :: Python :: 3.11
Classifier: Programming Language :: Python :: Implementation :: PyPy
Classifier: Programming Language :: Python :: Implementation :: CPython
Requires-Python: >=3.9
Requires-Dist: redis
Requires-Dist: nest-asyncio
